ibotcloud/__init__.py
ibotcloud/ask.py
ibotcloud/utils.py
ibotcloud/version.py
ibotcloud_python-0.1.3.dist-info/DESCRIPTION.rst
ibotcloud_python-0.1.3.dist-info/METADATA
ibotcloud_python-0.1.3.dist-info/RECORD
ibotcloud_python-0.1.3.dist-info/WHEEL
ibotcloud_python-0.1.3.dist-info/metadata.json
ibotcloud_python-0.1.3.dist-info/namespace_packages.txt
ibotcloud_python-0.1.3.dist-info/top_level.txt
