Metadata-Version: 2.0
Name: ibotcloud-python
Version: 0.1.3
Summary: xiaoi iBotCloud WebAPI Python SDK
Home-page: https://github.com/tanbro/ibotcloud-python
Author: liu xue yan
Author-email: liu_xue_yan@foxmail.com
License: UNKNOWN
Platform: UNKNOWN
Requires-Python: >=2.7
Requires-Dist: requests
Provides-Extra: develop
Requires-Dist: setuptools; extra == 'develop'
Requires-Dist: wheel; extra == 'develop'
Requires-Dist: twine; extra == 'develop'
Provides-Extra: docs
Requires-Dist: Sphinx; extra == 'docs'
Requires-Dist: sphinx-autobuild; extra == 'docs'
